{"cameraMode":{"drawMode":0,"name":"Shaded","section":"Shading Mode"},"sceneLighting":true,"audioPlay":false,"sceneViewState":{"m_AlwaysRefresh":false,"showFog":true,"showSkybox":true,"showFlares":true,"showImageEffects":true,"showParticleSystems":true,"showVisualEffectGraphs":true,"m_FxEnabled":true},"in2DMode":false,"pivot":{"x":-2.1071624755859377,"y":0.1383342742919922,"z":-5.916725158691406},"rotation":{"x":-0.06287937611341477,"y":0.933013379573822,"z":-0.20113250613212586,"w":-0.2916848361492157},"size":10.0,"orthographic":false}